pystargate/__init__.py
pystargate/config.py
pystargate/data.py
pystargate/files.py
pystargate/image.py
pystargate/input.py
pystargate/key.py
pystargate/keyboard.py
pystargate/machineSpeech.py
pystargate/machineVision.py
pystargate/mouse.py
pystargate/time.py
pystargate/user.py
pystargate/view.py
pystargate/window.py
pystargate/words.py
pystargate/libs/__init__.py
pystargate/libs/ai.py
pystargate/libs/autogui.py
pystargate/libs/camera.py
pystargate/libs/common.py
pystargate/libs/extend.py
pystargate/libs/opencv.py
pystargate/libs/pyredis.py
pystargate/libs/tkinter.py
stargatedb/__init__.py
stargatedb/cloud.py
stargatedb/user.py
pystargate-1.0.4.dist-info/LICENSE
pystargate-1.0.4.dist-info/METADATA
pystargate-1.0.4.dist-info/WHEEL
pystargate-1.0.4.dist-info/top_level.txt
pystargate-1.0.4.dist-info/RECORD
