Metadata-Version: 2.1
Name: pystargate
Version: 1.0.4
Summary: pyStargate engine is an open source (IPA) intelligent process automation development framework
Home-page: http://www.pystargate.com
Author: yangpai
Author-email: wumeng@mail.yangpai.co
License: UNKNOWN
Platform: UNKNOWN
Classifier: Programming Language :: Python :: 2
Classifier: Programming Language :: Python :: 3
Classifier: License :: OSI Approved :: MIT License
Classifier: Operating System :: OS Independent
Requires-Python: >=2.7
